<?xml version="1.0" encoding="utf-8"?>
<Messages>
	<Message severity="INFO" prefix="[SCHED 204-61]" key="SCHED_PIPELINING_STATUS_631" tag="SCHEDULE" content="Option &apos;relax_ii_for_timing&apos; is enabled, will increase II to preserve clock frequency constraints."/>
	<Message severity="INFO" prefix="[HLS 200-10]" key="HLS_10_1312" tag="" content="Analyzing design file &apos;topp.c&apos; ..."/>
	<Message severity="WARNING" prefix="[HLS 214-111]" key="HLS 214-111" tag="DATAFLOW,SDX_KERNEL" content="Static variables and non-static stream cannot be used inside a dataflow region: topp.c:469:15"/>
	<Message severity="WARNING" prefix="[HLS 200-471]" key="HLS 200-471" tag="DATAFLOW,SDX_KERNEL" content="Dataflow form checks found 1 issue(s) in file topp.c"/>
	<Message severity="INFO" prefix="[HLS 200-111]" key="HLS_111_965" tag="" content="Finished Linking Time (s): cpu = 00:00:01 ; elapsed = 00:00:03 . Memory (MB): peak = 103.801 ; gain = 18.781"/>
	<Message severity="INFO" prefix="[HLS 200-111]" key="HLS_111_965" tag="" content="Finished Checking Pragmas Time (s): cpu = 00:00:01 ; elapsed = 00:00:03 . Memory (MB): peak = 103.801 ; gain = 18.781"/>
	<Message severity="INFO" prefix="[HLS 200-10]" key="HLS_10_1467" tag="" content="Starting code transformations ..."/>
	<Message severity="INFO" prefix="[HLS 200-111]" key="HLS_111_965" tag="" content="Finished Standard Transforms Time (s): cpu = 00:00:01 ; elapsed = 00:00:04 . Memory (MB): peak = 106.430 ; gain = 21.410"/>
	<Message severity="INFO" prefix="[HLS 200-10]" key="HLS_10_1472" tag="" content="Checking synthesizability ..."/>
	<Message severity="INFO" prefix="[XFORM 203-602]" key="XFORM_AUTO_INLINE_STATUS_223" tag="" content="Inlining function &apos;sigmoid&apos; into &apos;detection_head&apos; (topp.c:454) automatically."/>
	<Message severity="INFO" prefix="[HLS 200-111]" key="HLS_111_965" tag="" content="Finished Checking Synthesizability Time (s): cpu = 00:00:01 ; elapsed = 00:00:04 . Memory (MB): peak = 106.887 ; gain = 21.867"/>
	<Message severity="INFO" prefix="[XFORM 203-102]" key="XFORM_AUTO_PARTITION_STATUS_121" tag="" content="Partitioning array &apos;linbu.7&apos; in dimension 1 automatically."/>
	<Message severity="INFO" prefix="[XFORM 203-102]" key="XFORM_AUTO_PARTITION_STATUS_121" tag="" content="Partitioning array &apos;linbu.6&apos; in dimension 1 automatically."/>
	<Message severity="INFO" prefix="[XFORM 203-102]" key="XFORM_AUTO_PARTITION_STATUS_121" tag="" content="Partitioning array &apos;linbu.5&apos; in dimension 1 automatically."/>
	<Message severity="INFO" prefix="[XFORM 203-102]" key="XFORM_AUTO_PARTITION_STATUS_121" tag="" content="Partitioning array &apos;linbu.4&apos; in dimension 1 automatically."/>
	<Message severity="INFO" prefix="[XFORM 203-102]" key="XFORM_AUTO_PARTITION_STATUS_121" tag="" content="Partitioning array &apos;linbu&apos; in dimension 1 automatically."/>
	<Message severity="INFO" prefix="[XFORM 203-602]" key="XFORM_AUTO_INLINE_STATUS_223" tag="" content="Inlining function &apos;sigmoid&apos; into &apos;detection_head&apos; (topp.c:454) automatically."/>
	<Message severity="WARNING" prefix="[XFORM 203-713]" key="XFORM_DATAFLOW_WARNING_193" tag="ARRAY,SDX_ARRAY,DATAFLOW" content="All the elements of global array &apos;f1&apos;  should be updated in process function &apos;conv1&apos;, otherwise it may not be synthesized correctly."/>
	<Message severity="WARNING" prefix="[XFORM 203-713]" key="XFORM_DATAFLOW_WARNING_193" tag="ARRAY,SDX_ARRAY,DATAFLOW" content="All the elements of global array &apos;f2&apos;  should be updated in process function &apos;conv2&apos;, otherwise it may not be synthesized correctly."/>
	<Message severity="WARNING" prefix="[XFORM 203-713]" key="XFORM_DATAFLOW_WARNING_193" tag="ARRAY,SDX_ARRAY,DATAFLOW" content="All the elements of global array &apos;f3&apos;  should be updated in process function &apos;conv3&apos;, otherwise it may not be synthesized correctly."/>
	<Message severity="WARNING" prefix="[XFORM 203-713]" key="XFORM_DATAFLOW_WARNING_193" tag="ARRAY,SDX_ARRAY,DATAFLOW" content="All the elements of global array &apos;f4&apos;  should be updated in process function &apos;conv4&apos;, otherwise it may not be synthesized correctly."/>
	<Message severity="WARNING" prefix="[XFORM 203-713]" key="XFORM_DATAFLOW_WARNING_193" tag="ARRAY,SDX_ARRAY,DATAFLOW" content="All the elements of global array &apos;f5&apos;  should be updated in process function &apos;conv5&apos;, otherwise it may not be synthesized correctly."/>
	<Message severity="WARNING" prefix="[XFORM 203-713]" key="XFORM_DATAFLOW_WARNING_193" tag="ARRAY,SDX_ARRAY,DATAFLOW" content="All the elements of global array &apos;output&apos; should be updated in process function &apos;detection_head&apos;, otherwise it may not be synthesized correctly."/>
	<Message severity="INFO" prefix="[XFORM 203-712]" key="XFORM_DATAFLOW_TRANSFORM_230" tag="DATAFLOW" content="Applying dataflow to function &apos;topp&apos;, detected/extracted 8 process function(s): 
	 &apos;conv1&apos;
	 &apos;maxpool1&apos;
	 &apos;conv2&apos;
	 &apos;maxpool2&apos;
	 &apos;conv3&apos;
	 &apos;conv4&apos;
	 &apos;conv5&apos;
	 &apos;detection_head&apos;."/>
	<Message severity="INFO" prefix="[HLS 200-111]" key="HLS_111_965" tag="" content="Finished Pre-synthesis Time (s): cpu = 00:00:01 ; elapsed = 00:00:05 . Memory (MB): peak = 128.820 ; gain = 43.801"/>
	<Message severity="INFO" prefix="[HLS 200-111]" key="HLS_111_965" tag="" content="Finished Architecture Synthesis Time (s): cpu = 00:00:08 ; elapsed = 00:00:12 . Memory (MB): peak = 212.410 ; gain = 127.391"/>
	<Message severity="INFO" prefix="[HLS 200-10]" key="HLS_10_1317" tag="" content="Starting hardware synthesis ..."/>
	<Message severity="INFO" prefix="[HLS 200-10]" key="HLS_10_1385" tag="" content="Synthesizing &apos;topp&apos; ..."/>
	<Message severity="WARNING" prefix="[SYN 201-107]" key="SYN_PORT_NAME_ILLEGAL_593" tag="" content="Renaming port name &apos;topp/image&apos; to &apos;topp/image_r&apos; to avoid the conflict with HDL keywords or other object names."/>
	<Message severity="WARNING" prefix="[SYN 201-107]" key="SYN_PORT_NAME_ILLEGAL_593" tag="" content="Renaming port name &apos;topp/output&apos; to &apos;topp/output_r&apos; to avoid the conflict with HDL keywords or other object names."/>
	<Message severity="INFO" prefix="[HLS 200-10]" key="HLS_10_1477" tag="" content="----------------------------------------------------------------"/>
	<Message severity="INFO" prefix="[HLS 200-42]" key="HLS_42_1438" tag="" content="-- Implementing module &apos;conv1&apos;"/>
	<Message severity="INFO" prefix="[HLS 200-10]" key="HLS_10_1478" tag="" content="----------------------------------------------------------------"/>
	<Message severity="INFO" prefix="[SCHED 204-11]" key="SCHED_SCHED_STATUS_597" tag="" content="Starting scheduling ..."/>
	<Message severity="INFO" prefix="[SCHED 204-11]" key="SCHED_SCHED_STATUS_596" tag="" content="Finished scheduling."/>
	<Message severity="INFO" prefix="[HLS 200-111]" key="HLS_111_966" tag="" content=" Elapsed time: 11.947 seconds; current allocated memory: 168.899 MB."/>
	<Message severity="INFO" prefix="[HLS 200-434]" key="HLS 200-434" tag="SDX" content="Only 0 loops out of a total 7 loops have been pipelined in this design."/>
	<Message severity="INFO" prefix="[BIND 205-100]" key="BIND_100_926" tag="" content="Starting micro-architecture generation ..."/>
	<Message severity="INFO" prefix="[BIND 205-101]" key="BIND_101_698" tag="" content="Performing variable lifetime analysis."/>
	<Message severity="INFO" prefix="[BIND 205-101]" key="BIND_101_697" tag="" content="Exploring resource sharing."/>
	<Message severity="INFO" prefix="[BIND 205-101]" key="BIND_101_693" tag="" content="Binding ..."/>
	<Message severity="INFO" prefix="[BIND 205-100]" key="BIND_100_925" tag="" content="Finished micro-architecture generation."/>
	<Message severity="INFO" prefix="[HLS 200-111]" key="HLS_111_966" tag="" content=" Elapsed time: 0.194 seconds; current allocated memory: 169.418 MB."/>
	<Message severity="INFO" prefix="[HLS 200-10]" key="HLS_10_1477" tag="" content="----------------------------------------------------------------"/>
	<Message severity="INFO" prefix="[HLS 200-42]" key="HLS_42_1438" tag="" content="-- Implementing module &apos;maxpool1&apos;"/>
	<Message severity="INFO" prefix="[HLS 200-10]" key="HLS_10_1478" tag="" content="----------------------------------------------------------------"/>
	<Message severity="INFO" prefix="[SCHED 204-11]" key="SCHED_SCHED_STATUS_597" tag="" content="Starting scheduling ..."/>
	<Message severity="INFO" prefix="[SCHED 204-11]" key="SCHED_SCHED_STATUS_596" tag="" content="Finished scheduling."/>
	<Message severity="INFO" prefix="[HLS 200-111]" key="HLS_111_966" tag="" content=" Elapsed time: 0.206 seconds; current allocated memory: 169.801 MB."/>
	<Message severity="INFO" prefix="[BIND 205-100]" key="BIND_100_926" tag="" content="Starting micro-architecture generation ..."/>
	<Message severity="INFO" prefix="[BIND 205-101]" key="BIND_101_698" tag="" content="Performing variable lifetime analysis."/>
	<Message severity="INFO" prefix="[BIND 205-101]" key="BIND_101_697" tag="" content="Exploring resource sharing."/>
	<Message severity="INFO" prefix="[BIND 205-101]" key="BIND_101_693" tag="" content="Binding ..."/>
	<Message severity="INFO" prefix="[BIND 205-100]" key="BIND_100_925" tag="" content="Finished micro-architecture generation."/>
	<Message severity="INFO" prefix="[HLS 200-111]" key="HLS_111_966" tag="" content=" Elapsed time: 0.134 seconds; current allocated memory: 170.244 MB."/>
	<Message severity="INFO" prefix="[HLS 200-10]" key="HLS_10_1477" tag="" content="----------------------------------------------------------------"/>
	<Message severity="INFO" prefix="[HLS 200-42]" key="HLS_42_1438" tag="" content="-- Implementing module &apos;conv2&apos;"/>
	<Message severity="INFO" prefix="[HLS 200-10]" key="HLS_10_1478" tag="" content="----------------------------------------------------------------"/>
	<Message severity="INFO" prefix="[SCHED 204-11]" key="SCHED_SCHED_STATUS_597" tag="" content="Starting scheduling ..."/>
	<Message severity="INFO" prefix="[SCHED 204-11]" key="SCHED_SCHED_STATUS_596" tag="" content="Finished scheduling."/>
	<Message severity="INFO" prefix="[HLS 200-111]" key="HLS_111_966" tag="" content=" Elapsed time: 0.55 seconds; current allocated memory: 170.714 MB."/>
	<Message severity="INFO" prefix="[BIND 205-100]" key="BIND_100_926" tag="" content="Starting micro-architecture generation ..."/>
	<Message severity="INFO" prefix="[BIND 205-101]" key="BIND_101_698" tag="" content="Performing variable lifetime analysis."/>
	<Message severity="INFO" prefix="[BIND 205-101]" key="BIND_101_697" tag="" content="Exploring resource sharing."/>
	<Message severity="INFO" prefix="[BIND 205-101]" key="BIND_101_693" tag="" content="Binding ..."/>
	<Message severity="INFO" prefix="[BIND 205-100]" key="BIND_100_925" tag="" content="Finished micro-architecture generation."/>
	<Message severity="INFO" prefix="[HLS 200-111]" key="HLS_111_966" tag="" content=" Elapsed time: 0.257 seconds; current allocated memory: 171.193 MB."/>
	<Message severity="INFO" prefix="[HLS 200-10]" key="HLS_10_1477" tag="" content="----------------------------------------------------------------"/>
	<Message severity="INFO" prefix="[HLS 200-42]" key="HLS_42_1438" tag="" content="-- Implementing module &apos;maxpool2&apos;"/>
	<Message severity="INFO" prefix="[HLS 200-10]" key="HLS_10_1478" tag="" content="----------------------------------------------------------------"/>
	<Message severity="INFO" prefix="[SCHED 204-11]" key="SCHED_SCHED_STATUS_597" tag="" content="Starting scheduling ..."/>
	<Message severity="INFO" prefix="[SCHED 204-11]" key="SCHED_SCHED_STATUS_596" tag="" content="Finished scheduling."/>
	<Message severity="INFO" prefix="[HLS 200-111]" key="HLS_111_966" tag="" content=" Elapsed time: 0.447 seconds; current allocated memory: 171.601 MB."/>
	<Message severity="INFO" prefix="[BIND 205-100]" key="BIND_100_926" tag="" content="Starting micro-architecture generation ..."/>
	<Message severity="INFO" prefix="[BIND 205-101]" key="BIND_101_698" tag="" content="Performing variable lifetime analysis."/>
	<Message severity="INFO" prefix="[BIND 205-101]" key="BIND_101_697" tag="" content="Exploring resource sharing."/>
	<Message severity="INFO" prefix="[BIND 205-101]" key="BIND_101_693" tag="" content="Binding ..."/>
	<Message severity="INFO" prefix="[BIND 205-100]" key="BIND_100_925" tag="" content="Finished micro-architecture generation."/>
	<Message severity="INFO" prefix="[HLS 200-111]" key="HLS_111_966" tag="" content=" Elapsed time: 0.261 seconds; current allocated memory: 171.974 MB."/>
	<Message severity="INFO" prefix="[HLS 200-10]" key="HLS_10_1477" tag="" content="----------------------------------------------------------------"/>
	<Message severity="INFO" prefix="[HLS 200-42]" key="HLS_42_1438" tag="" content="-- Implementing module &apos;conv3&apos;"/>
	<Message severity="INFO" prefix="[HLS 200-10]" key="HLS_10_1478" tag="" content="----------------------------------------------------------------"/>
	<Message severity="INFO" prefix="[SCHED 204-11]" key="SCHED_SCHED_STATUS_597" tag="" content="Starting scheduling ..."/>
	<Message severity="INFO" prefix="[SCHED 204-11]" key="SCHED_SCHED_STATUS_596" tag="" content="Finished scheduling."/>
	<Message severity="INFO" prefix="[HLS 200-111]" key="HLS_111_966" tag="" content=" Elapsed time: 0.365 seconds; current allocated memory: 172.437 MB."/>
	<Message severity="INFO" prefix="[BIND 205-100]" key="BIND_100_926" tag="" content="Starting micro-architecture generation ..."/>
	<Message severity="INFO" prefix="[BIND 205-101]" key="BIND_101_698" tag="" content="Performing variable lifetime analysis."/>
	<Message severity="INFO" prefix="[BIND 205-101]" key="BIND_101_697" tag="" content="Exploring resource sharing."/>
	<Message severity="INFO" prefix="[BIND 205-101]" key="BIND_101_693" tag="" content="Binding ..."/>
	<Message severity="INFO" prefix="[BIND 205-100]" key="BIND_100_925" tag="" content="Finished micro-architecture generation."/>
	<Message severity="INFO" prefix="[HLS 200-111]" key="HLS_111_966" tag="" content=" Elapsed time: 0.17 seconds; current allocated memory: 172.927 MB."/>
	<Message severity="INFO" prefix="[HLS 200-10]" key="HLS_10_1477" tag="" content="----------------------------------------------------------------"/>
	<Message severity="INFO" prefix="[HLS 200-42]" key="HLS_42_1438" tag="" content="-- Implementing module &apos;conv4&apos;"/>
	<Message severity="INFO" prefix="[HLS 200-10]" key="HLS_10_1478" tag="" content="----------------------------------------------------------------"/>
	<Message severity="INFO" prefix="[SCHED 204-11]" key="SCHED_SCHED_STATUS_597" tag="" content="Starting scheduling ..."/>
	<Message severity="INFO" prefix="[SCHED 204-11]" key="SCHED_SCHED_STATUS_596" tag="" content="Finished scheduling."/>
	<Message severity="INFO" prefix="[HLS 200-111]" key="HLS_111_966" tag="" content=" Elapsed time: 0.246 seconds; current allocated memory: 173.353 MB."/>
	<Message severity="INFO" prefix="[BIND 205-100]" key="BIND_100_926" tag="" content="Starting micro-architecture generation ..."/>
	<Message severity="INFO" prefix="[BIND 205-101]" key="BIND_101_698" tag="" content="Performing variable lifetime analysis."/>
	<Message severity="INFO" prefix="[BIND 205-101]" key="BIND_101_697" tag="" content="Exploring resource sharing."/>
	<Message severity="INFO" prefix="[BIND 205-101]" key="BIND_101_693" tag="" content="Binding ..."/>
	<Message severity="INFO" prefix="[BIND 205-100]" key="BIND_100_925" tag="" content="Finished micro-architecture generation."/>
	<Message severity="INFO" prefix="[HLS 200-111]" key="HLS_111_966" tag="" content=" Elapsed time: 0.166 seconds; current allocated memory: 173.842 MB."/>
	<Message severity="INFO" prefix="[HLS 200-10]" key="HLS_10_1477" tag="" content="----------------------------------------------------------------"/>
	<Message severity="INFO" prefix="[HLS 200-42]" key="HLS_42_1438" tag="" content="-- Implementing module &apos;conv5&apos;"/>
	<Message severity="INFO" prefix="[HLS 200-10]" key="HLS_10_1478" tag="" content="----------------------------------------------------------------"/>
	<Message severity="INFO" prefix="[SCHED 204-11]" key="SCHED_SCHED_STATUS_597" tag="" content="Starting scheduling ..."/>
	<Message severity="INFO" prefix="[SCHED 204-11]" key="SCHED_SCHED_STATUS_596" tag="" content="Finished scheduling."/>
	<Message severity="INFO" prefix="[HLS 200-111]" key="HLS_111_966" tag="" content=" Elapsed time: 0.242 seconds; current allocated memory: 174.228 MB."/>
	<Message severity="INFO" prefix="[BIND 205-100]" key="BIND_100_926" tag="" content="Starting micro-architecture generation ..."/>
	<Message severity="INFO" prefix="[BIND 205-101]" key="BIND_101_698" tag="" content="Performing variable lifetime analysis."/>
	<Message severity="INFO" prefix="[BIND 205-101]" key="BIND_101_697" tag="" content="Exploring resource sharing."/>
	<Message severity="INFO" prefix="[BIND 205-101]" key="BIND_101_693" tag="" content="Binding ..."/>
	<Message severity="INFO" prefix="[BIND 205-100]" key="BIND_100_925" tag="" content="Finished micro-architecture generation."/>
	<Message severity="INFO" prefix="[HLS 200-111]" key="HLS_111_966" tag="" content=" Elapsed time: 0.165 seconds; current allocated memory: 174.682 MB."/>
	<Message severity="INFO" prefix="[HLS 200-10]" key="HLS_10_1477" tag="" content="----------------------------------------------------------------"/>
	<Message severity="INFO" prefix="[HLS 200-42]" key="HLS_42_1438" tag="" content="-- Implementing module &apos;detection_head&apos;"/>
	<Message severity="INFO" prefix="[HLS 200-10]" key="HLS_10_1478" tag="" content="----------------------------------------------------------------"/>
	<Message severity="INFO" prefix="[SCHED 204-11]" key="SCHED_SCHED_STATUS_597" tag="" content="Starting scheduling ..."/>
	<Message severity="INFO" prefix="[SCHED 204-11]" key="SCHED_SCHED_STATUS_596" tag="" content="Finished scheduling."/>
	<Message severity="INFO" prefix="[HLS 200-111]" key="HLS_111_966" tag="" content=" Elapsed time: 0.195 seconds; current allocated memory: 175.018 MB."/>
	<Message severity="INFO" prefix="[BIND 205-100]" key="BIND_100_926" tag="" content="Starting micro-architecture generation ..."/>
	<Message severity="INFO" prefix="[BIND 205-101]" key="BIND_101_698" tag="" content="Performing variable lifetime analysis."/>
	<Message severity="INFO" prefix="[BIND 205-101]" key="BIND_101_697" tag="" content="Exploring resource sharing."/>
	<Message severity="INFO" prefix="[BIND 205-101]" key="BIND_101_693" tag="" content="Binding ..."/>
	<Message severity="INFO" prefix="[BIND 205-100]" key="BIND_100_925" tag="" content="Finished micro-architecture generation."/>
	<Message severity="INFO" prefix="[HLS 200-111]" key="HLS_111_966" tag="" content=" Elapsed time: 0.164 seconds; current allocated memory: 175.418 MB."/>
	<Message severity="INFO" prefix="[HLS 200-10]" key="HLS_10_1477" tag="" content="----------------------------------------------------------------"/>
	<Message severity="INFO" prefix="[HLS 200-42]" key="HLS_42_1438" tag="" content="-- Implementing module &apos;topp&apos;"/>
	<Message severity="INFO" prefix="[HLS 200-10]" key="HLS_10_1478" tag="" content="----------------------------------------------------------------"/>
	<Message severity="INFO" prefix="[SCHED 204-11]" key="SCHED_SCHED_STATUS_597" tag="" content="Starting scheduling ..."/>
	<Message severity="INFO" prefix="[SCHED 204-11]" key="SCHED_SCHED_STATUS_596" tag="" content="Finished scheduling."/>
	<Message severity="INFO" prefix="[HLS 200-111]" key="HLS_111_966" tag="" content=" Elapsed time: 0.171 seconds; current allocated memory: 175.489 MB."/>
	<Message severity="INFO" prefix="[BIND 205-100]" key="BIND_100_926" tag="" content="Starting micro-architecture generation ..."/>
	<Message severity="INFO" prefix="[BIND 205-101]" key="BIND_101_698" tag="" content="Performing variable lifetime analysis."/>
	<Message severity="INFO" prefix="[BIND 205-101]" key="BIND_101_697" tag="" content="Exploring resource sharing."/>
	<Message severity="INFO" prefix="[BIND 205-101]" key="BIND_101_693" tag="" content="Binding ..."/>
	<Message severity="INFO" prefix="[BIND 205-100]" key="BIND_100_925" tag="" content="Finished micro-architecture generation."/>
	<Message severity="INFO" prefix="[HLS 200-111]" key="HLS_111_966" tag="" content=" Elapsed time: 0.722 seconds; current allocated memory: 176.283 MB."/>
	<Message severity="INFO" prefix="[HLS 200-10]" key="HLS_10_1483" tag="" content="----------------------------------------------------------------"/>
	<Message severity="INFO" prefix="[HLS 200-10]" key="HLS_10_1484" tag="" content="-- Generating RTL for module &apos;conv1&apos;"/>
	<Message severity="INFO" prefix="[HLS 200-10]" key="HLS_10_1485" tag="" content="----------------------------------------------------------------"/>
	<Message severity="INFO" prefix="[SYN 201-210]" key="SYN_210_889" tag="" content="Renamed object name &apos;topp_fadd_32ns_32ns_32_5_full_dsp_1&apos; to &apos;topp_fadd_32ns_32bkb&apos; due to the length limit 20"/>
	<Message severity="INFO" prefix="[SYN 201-210]" key="SYN_210_889" tag="" content="Renamed object name &apos;topp_fmul_32ns_32ns_32_4_max_dsp_1&apos; to &apos;topp_fmul_32ns_32cud&apos; due to the length limit 20"/>
	<Message severity="INFO" prefix="[SYN 201-210]" key="SYN_210_889" tag="" content="Renamed object name &apos;topp_fcmp_32ns_32ns_1_1_1&apos; to &apos;topp_fcmp_32ns_32dEe&apos; due to the length limit 20"/>
	<Message severity="INFO" prefix="[RTGEN 206-100]" key="RTGEN_100_855" tag="" content="Generating core module &apos;topp_fadd_32ns_32bkb&apos;: 1 instance(s)."/>
	<Message severity="INFO" prefix="[RTGEN 206-100]" key="RTGEN_100_855" tag="" content="Generating core module &apos;topp_fcmp_32ns_32dEe&apos;: 1 instance(s)."/>
	<Message severity="INFO" prefix="[RTGEN 206-100]" key="RTGEN_100_855" tag="" content="Generating core module &apos;topp_fmul_32ns_32cud&apos;: 1 instance(s)."/>
	<Message severity="INFO" prefix="[RTGEN 206-100]" key="RTGEN_100_856" tag="" content="Finished creating RTL model for &apos;conv1&apos;."/>
	<Message severity="INFO" prefix="[HLS 200-111]" key="HLS_111_966" tag="" content=" Elapsed time: 0.51 seconds; current allocated memory: 177.540 MB."/>
	<Message severity="INFO" prefix="[HLS 200-10]" key="HLS_10_1483" tag="" content="----------------------------------------------------------------"/>
	<Message severity="INFO" prefix="[HLS 200-10]" key="HLS_10_1484" tag="" content="-- Generating RTL for module &apos;maxpool1&apos;"/>
	<Message severity="INFO" prefix="[HLS 200-10]" key="HLS_10_1485" tag="" content="----------------------------------------------------------------"/>
	<Message severity="INFO" prefix="[RTGEN 206-100]" key="RTGEN_100_855" tag="" content="Generating core module &apos;topp_fcmp_32ns_32dEe&apos;: 1 instance(s)."/>
	<Message severity="INFO" prefix="[RTGEN 206-100]" key="RTGEN_100_856" tag="" content="Finished creating RTL model for &apos;maxpool1&apos;."/>
	<Message severity="INFO" prefix="[HLS 200-111]" key="HLS_111_966" tag="" content=" Elapsed time: 0.404 seconds; current allocated memory: 178.542 MB."/>
	<Message severity="INFO" prefix="[HLS 200-10]" key="HLS_10_1483" tag="" content="----------------------------------------------------------------"/>
	<Message severity="INFO" prefix="[HLS 200-10]" key="HLS_10_1484" tag="" content="-- Generating RTL for module &apos;conv2&apos;"/>
	<Message severity="INFO" prefix="[HLS 200-10]" key="HLS_10_1485" tag="" content="----------------------------------------------------------------"/>
	<Message severity="INFO" prefix="[SYN 201-210]" key="SYN_210_889" tag="" content="Renamed object name &apos;topp_am_addmul_5ns_2s_6ns_11_1_1&apos; to &apos;topp_am_addmul_5neOg&apos; due to the length limit 20"/>
	<Message severity="INFO" prefix="[RTGEN 206-100]" key="RTGEN_100_855" tag="" content="Generating core module &apos;topp_am_addmul_5neOg&apos;: 1 instance(s)."/>
	<Message severity="INFO" prefix="[RTGEN 206-100]" key="RTGEN_100_855" tag="" content="Generating core module &apos;topp_fadd_32ns_32bkb&apos;: 1 instance(s)."/>
	<Message severity="INFO" prefix="[RTGEN 206-100]" key="RTGEN_100_855" tag="" content="Generating core module &apos;topp_fcmp_32ns_32dEe&apos;: 1 instance(s)."/>
	<Message severity="INFO" prefix="[RTGEN 206-100]" key="RTGEN_100_855" tag="" content="Generating core module &apos;topp_fmul_32ns_32cud&apos;: 1 instance(s)."/>
	<Message severity="INFO" prefix="[RTGEN 206-100]" key="RTGEN_100_856" tag="" content="Finished creating RTL model for &apos;conv2&apos;."/>
	<Message severity="INFO" prefix="[HLS 200-111]" key="HLS_111_966" tag="" content=" Elapsed time: 0.486 seconds; current allocated memory: 179.671 MB."/>
	<Message severity="INFO" prefix="[HLS 200-10]" key="HLS_10_1483" tag="" content="----------------------------------------------------------------"/>
	<Message severity="INFO" prefix="[HLS 200-10]" key="HLS_10_1484" tag="" content="-- Generating RTL for module &apos;maxpool2&apos;"/>
	<Message severity="INFO" prefix="[HLS 200-10]" key="HLS_10_1485" tag="" content="----------------------------------------------------------------"/>
	<Message severity="INFO" prefix="[RTGEN 206-100]" key="RTGEN_100_855" tag="" content="Generating core module &apos;topp_fcmp_32ns_32dEe&apos;: 1 instance(s)."/>
	<Message severity="INFO" prefix="[RTGEN 206-100]" key="RTGEN_100_856" tag="" content="Finished creating RTL model for &apos;maxpool2&apos;."/>
	<Message severity="INFO" prefix="[HLS 200-111]" key="HLS_111_966" tag="" content=" Elapsed time: 0.38 seconds; current allocated memory: 180.602 MB."/>
	<Message severity="INFO" prefix="[HLS 200-10]" key="HLS_10_1483" tag="" content="----------------------------------------------------------------"/>
	<Message severity="INFO" prefix="[HLS 200-10]" key="HLS_10_1484" tag="" content="-- Generating RTL for module &apos;conv3&apos;"/>
	<Message severity="INFO" prefix="[HLS 200-10]" key="HLS_10_1485" tag="" content="----------------------------------------------------------------"/>
	<Message severity="INFO" prefix="[RTGEN 206-100]" key="RTGEN_100_855" tag="" content="Generating core module &apos;topp_fadd_32ns_32bkb&apos;: 1 instance(s)."/>
	<Message severity="INFO" prefix="[RTGEN 206-100]" key="RTGEN_100_855" tag="" content="Generating core module &apos;topp_fcmp_32ns_32dEe&apos;: 1 instance(s)."/>
	<Message severity="INFO" prefix="[RTGEN 206-100]" key="RTGEN_100_855" tag="" content="Generating core module &apos;topp_fmul_32ns_32cud&apos;: 1 instance(s)."/>
	<Message severity="INFO" prefix="[RTGEN 206-100]" key="RTGEN_100_856" tag="" content="Finished creating RTL model for &apos;conv3&apos;."/>
	<Message severity="INFO" prefix="[HLS 200-111]" key="HLS_111_966" tag="" content=" Elapsed time: 0.394 seconds; current allocated memory: 181.757 MB."/>
	<Message severity="INFO" prefix="[HLS 200-10]" key="HLS_10_1483" tag="" content="----------------------------------------------------------------"/>
	<Message severity="INFO" prefix="[HLS 200-10]" key="HLS_10_1484" tag="" content="-- Generating RTL for module &apos;conv4&apos;"/>
	<Message severity="INFO" prefix="[HLS 200-10]" key="HLS_10_1485" tag="" content="----------------------------------------------------------------"/>
	<Message severity="INFO" prefix="[RTGEN 206-100]" key="RTGEN_100_855" tag="" content="Generating core module &apos;topp_fadd_32ns_32bkb&apos;: 1 instance(s)."/>
	<Message severity="INFO" prefix="[RTGEN 206-100]" key="RTGEN_100_855" tag="" content="Generating core module &apos;topp_fcmp_32ns_32dEe&apos;: 1 instance(s)."/>
	<Message severity="INFO" prefix="[RTGEN 206-100]" key="RTGEN_100_855" tag="" content="Generating core module &apos;topp_fmul_32ns_32cud&apos;: 1 instance(s)."/>
	<Message severity="INFO" prefix="[RTGEN 206-100]" key="RTGEN_100_856" tag="" content="Finished creating RTL model for &apos;conv4&apos;."/>
	<Message severity="INFO" prefix="[HLS 200-111]" key="HLS_111_966" tag="" content=" Elapsed time: 0.457 seconds; current allocated memory: 182.910 MB."/>
	<Message severity="INFO" prefix="[HLS 200-10]" key="HLS_10_1483" tag="" content="----------------------------------------------------------------"/>
	<Message severity="INFO" prefix="[HLS 200-10]" key="HLS_10_1484" tag="" content="-- Generating RTL for module &apos;conv5&apos;"/>
	<Message severity="INFO" prefix="[HLS 200-10]" key="HLS_10_1485" tag="" content="----------------------------------------------------------------"/>
	<Message severity="INFO" prefix="[RTGEN 206-100]" key="RTGEN_100_855" tag="" content="Generating core module &apos;topp_fadd_32ns_32bkb&apos;: 1 instance(s)."/>
	<Message severity="INFO" prefix="[RTGEN 206-100]" key="RTGEN_100_855" tag="" content="Generating core module &apos;topp_fmul_32ns_32cud&apos;: 1 instance(s)."/>
	<Message severity="INFO" prefix="[RTGEN 206-100]" key="RTGEN_100_856" tag="" content="Finished creating RTL model for &apos;conv5&apos;."/>
	<Message severity="INFO" prefix="[HLS 200-111]" key="HLS_111_966" tag="" content=" Elapsed time: 0.427 seconds; current allocated memory: 183.938 MB."/>
	<Message severity="INFO" prefix="[HLS 200-10]" key="HLS_10_1483" tag="" content="----------------------------------------------------------------"/>
	<Message severity="INFO" prefix="[HLS 200-10]" key="HLS_10_1484" tag="" content="-- Generating RTL for module &apos;detection_head&apos;"/>
	<Message severity="INFO" prefix="[HLS 200-10]" key="HLS_10_1485" tag="" content="----------------------------------------------------------------"/>
	<Message severity="INFO" prefix="[SYN 201-210]" key="SYN_210_889" tag="" content="Renamed object name &apos;topp_fdiv_32ns_32ns_32_16_1&apos; to &apos;topp_fdiv_32ns_32fYi&apos; due to the length limit 20"/>
	<Message severity="INFO" prefix="[SYN 201-210]" key="SYN_210_889" tag="" content="Renamed object name &apos;topp_fexp_32ns_32ns_32_9_full_dsp_1&apos; to &apos;topp_fexp_32ns_32g8j&apos; due to the length limit 20"/>
	<Message severity="INFO" prefix="[RTGEN 206-100]" key="RTGEN_100_855" tag="" content="Generating core module &apos;topp_fadd_32ns_32bkb&apos;: 1 instance(s)."/>
	<Message severity="INFO" prefix="[RTGEN 206-100]" key="RTGEN_100_855" tag="" content="Generating core module &apos;topp_fdiv_32ns_32fYi&apos;: 1 instance(s)."/>
	<Message severity="INFO" prefix="[RTGEN 206-100]" key="RTGEN_100_855" tag="" content="Generating core module &apos;topp_fexp_32ns_32g8j&apos;: 1 instance(s)."/>
	<Message severity="INFO" prefix="[RTGEN 206-100]" key="RTGEN_100_855" tag="" content="Generating core module &apos;topp_fmul_32ns_32cud&apos;: 1 instance(s)."/>
	<Message severity="INFO" prefix="[RTGEN 206-100]" key="RTGEN_100_856" tag="" content="Finished creating RTL model for &apos;detection_head&apos;."/>
	<Message severity="INFO" prefix="[HLS 200-111]" key="HLS_111_966" tag="" content=" Elapsed time: 0.499 seconds; current allocated memory: 184.909 MB."/>
	<Message severity="INFO" prefix="[HLS 200-10]" key="HLS_10_1483" tag="" content="----------------------------------------------------------------"/>
	<Message severity="INFO" prefix="[HLS 200-10]" key="HLS_10_1484" tag="" content="-- Generating RTL for module &apos;topp&apos;"/>
	<Message severity="INFO" prefix="[HLS 200-10]" key="HLS_10_1485" tag="" content="----------------------------------------------------------------"/>
	<Message severity="INFO" prefix="[RTGEN 206-500]" key="PREPROC_IO_COMP_CONFLICT_1950" tag="" content="Setting interface mode on port &apos;topp/image_r&apos; to &apos;ap_memory&apos;."/>
	<Message severity="INFO" prefix="[RTGEN 206-500]" key="PREPROC_IO_COMP_CONFLICT_1950" tag="" content="Setting interface mode on port &apos;topp/output_r&apos; to &apos;ap_memory&apos;."/>
	<Message severity="INFO" prefix="[RTGEN 206-500]" key="PREPROC_IO_COMP_CONFLICT_1950" tag="" content="Setting interface mode on function &apos;topp&apos; to &apos;ap_ctrl_hs&apos;."/>
	<Message severity="INFO" prefix="[RTGEN 206-100]" key="RTGEN_100_856" tag="" content="Finished creating RTL model for &apos;topp&apos;."/>
	<Message severity="INFO" prefix="[HLS 200-111]" key="HLS_111_966" tag="" content=" Elapsed time: 0.42 seconds; current allocated memory: 185.851 MB."/>
	<Message severity="INFO" prefix="[RTMG 210-278]" key="RTMG_278_1792" tag="" content="Implementing memory &apos;conv1_linbu_4_0_ram (RAM)&apos; using block RAMs with power-on initialization."/>
	<Message severity="INFO" prefix="[RTMG 210-278]" key="RTMG_278_1790" tag="" content="Implementing memory &apos;conv1_win_buf_ram (RAM)&apos; using block RAMs."/>
	<Message severity="INFO" prefix="[RTMG 210-278]" key="RTMG_278_1792" tag="" content="Implementing memory &apos;conv2_linbu_5_0_ram (RAM)&apos; using block RAMs with power-on initialization."/>
	<Message severity="INFO" prefix="[RTMG 210-278]" key="RTMG_278_1790" tag="" content="Implementing memory &apos;conv2_win_buf_ram (RAM)&apos; using block RAMs."/>
	<Message severity="INFO" prefix="[RTMG 210-278]" key="RTMG_278_1792" tag="" content="Implementing memory &apos;conv3_linbu_6_0_ram (RAM)&apos; using block RAMs with power-on initialization."/>
	<Message severity="INFO" prefix="[RTMG 210-278]" key="RTMG_278_1790" tag="" content="Implementing memory &apos;conv3_win_buf_ram (RAM)&apos; using block RAMs."/>
	<Message severity="INFO" prefix="[RTMG 210-278]" key="RTMG_278_1792" tag="" content="Implementing memory &apos;conv4_linbu_7_0_ram (RAM)&apos; using block RAMs with power-on initialization."/>
	<Message severity="INFO" prefix="[RTMG 210-278]" key="RTMG_278_1790" tag="" content="Implementing memory &apos;conv4_win_buf_ram (RAM)&apos; using block RAMs."/>
	<Message severity="INFO" prefix="[RTMG 210-278]" key="RTMG_278_1792" tag="" content="Implementing memory &apos;conv5_linbu_0_ram (RAM)&apos; using block RAMs with power-on initialization."/>
	<Message severity="INFO" prefix="[RTMG 210-278]" key="RTMG_278_1790" tag="" content="Implementing memory &apos;detection_head_sum_ram (RAM)&apos; using distributed RAMs."/>
	<Message severity="INFO" prefix="[RTMG 210-278]" key="RTMG_278_1792" tag="" content="Implementing memory &apos;topp_f1_memcore_ram (RAM)&apos; using block RAMs with power-on initialization."/>
	<Message severity="INFO" prefix="[RTMG 210-278]" key="RTMG_278_1792" tag="" content="Implementing memory &apos;topp_p1_memcore_ram (RAM)&apos; using block RAMs with power-on initialization."/>
	<Message severity="INFO" prefix="[RTMG 210-278]" key="RTMG_278_1792" tag="" content="Implementing memory &apos;topp_f2_memcore_ram (RAM)&apos; using block RAMs with power-on initialization."/>
	<Message severity="INFO" prefix="[RTMG 210-278]" key="RTMG_278_1792" tag="" content="Implementing memory &apos;topp_p2_memcore_ram (RAM)&apos; using block RAMs with power-on initialization."/>
	<Message severity="INFO" prefix="[RTMG 210-278]" key="RTMG_278_1792" tag="" content="Implementing memory &apos;topp_f3_memcore_ram (RAM)&apos; using block RAMs with power-on initialization."/>
	<Message severity="INFO" prefix="[RTMG 210-278]" key="RTMG_278_1792" tag="" content="Implementing memory &apos;topp_f4_memcore_ram (RAM)&apos; using block RAMs with power-on initialization."/>
	<Message severity="INFO" prefix="[RTMG 210-278]" key="RTMG_278_1792" tag="" content="Implementing memory &apos;topp_f5_memcore_ram (RAM)&apos; using block RAMs with power-on initialization."/>
	<Message severity="INFO" prefix="[HLS 200-111]" key="HLS_111_965" tag="" content="Finished generating all RTL models Time (s): cpu = 00:00:15 ; elapsed = 00:00:27 . Memory (MB): peak = 258.602 ; gain = 173.582"/>
	<Message severity="INFO" prefix="[SYSC 207-301]" key="SYSC_301_1065" tag="" content="Generating SystemC RTL for topp."/>
	<Message severity="INFO" prefix="[VHDL 208-304]" key="VHDL_304_1066" tag="" content="Generating VHDL RTL for topp."/>
	<Message severity="INFO" prefix="[VLOG 209-307]" key="VLOG_307_1067" tag="" content="Generating Verilog RTL for topp."/>
	<Message severity="INFO" prefix="[HLS 200-112]" key="HLS_112_964" tag="" content="Total elapsed time: 27.405 seconds; peak allocated memory: 185.851 MB."/>
</Messages>
